document_vision/__init__.py
document_vision-0.0.1.dist-info/LICENSE
document_vision-0.0.1.dist-info/WHEEL
document_vision-0.0.1.dist-info/METADATA
document_vision-0.0.1.dist-info/RECORD
