Metadata-Version: 2.1
Name: document-vision
Version: 0.0.1
Summary: Application to visually read and understand document images using machine learning
Home-page: https://github.com/dcooper01/document-vision
License: MIT
Author: Daniel
Author-email: dcooper01sp@protonmail.com
Maintainer: Daniel
Maintainer-email: dcooper01sp@protonmail.com
Requires-Python: >=3.8,<4.0
Classifier: License :: OSI Approved :: MIT License
Classifier: Programming Language :: Python :: 3
Classifier: Programming Language :: Python :: 3.8
Project-URL: Repository, https://github.com/dcooper01/document-vision
